{
  "project_info": {
    "project_number": "728183562430",
    "project_id": "homezapp-c08b6",
    "storage_bucket": "homezapp-c08b6.appspot.com"
  },
  "client": [
    {
      "client_info": {
        "mobilesdk_app_id": "1:728183562430:android:16b0b601441aaaa6567eef",
        "android_client_info": {
          "package_name": "com.example.homezapp"
        }
      },
      "oauth_client": [
        {
          "client_id": "728183562430-i6lr4v9spikdrv63v80bfgqlie3tumss.apps.googleusercontent.com",
          "client_type": 3
        }
      ],
      "api_key": [
        {
          "current_key": "AIzaSyBJ6IeoEU-Slh5Mfx_h7BghyZedQtqwABQ"
        }
      ],
      "services": {
        "appinvite_service": {
          "other_platform_oauth_client": [
            {
              "client_id": "728183562430-i6lr4v9spikdrv63v80bfgqlie3tumss.apps.googleusercontent.com",
              "client_type": 3
            }
          ]
        }
      }
    }
  ],
  "configuration_version": "1"
}